usgsxplore/__init__.py
usgsxplore/api.py
usgsxplore/cli.py
usgsxplore/errors.py
usgsxplore/filter.py
usgsxplore/utils.py
usgsxplore/vizualisation.py
usgsxplore-1.0.8.dist-info/METADATA
usgsxplore-1.0.8.dist-info/WHEEL
usgsxplore-1.0.8.dist-info/entry_points.txt
usgsxplore-1.0.8.dist-info/licenses/LICENSE
usgsxplore-1.0.8.dist-info/RECORD
