Metadata-Version: 2.4
Name: usgsxplore
Version: 1.0.8
Summary: Search and download data or scenes from USGS API
License: MIT
License-File: LICENSE
Keywords: earth observation,remote sesing,GIS,satellite imagery,USGS,M2M
Author: Godin Luc
Author-email: godin.luc2002@gmail.com
Maintainer: Amaury Dehecq
Maintainer-email: this-is-not-an-email@a.com
Requires-Python: >=3.10,<4.0
Classifier: License :: OSI Approved :: MIT License
Classifier: Programming Language :: Python :: 3
Classifier: Programming Language :: Python :: 3.10
Classifier: Programming Language :: Python :: 3.11
Classifier: Programming Language :: Python :: 3.12
Classifier: Programming Language :: Python :: 3.13
Classifier: Programming Language :: Python :: 3.14
Requires-Dist: click (>=8.1.7,<9.0.0)
Requires-Dist: folium (>=0.19.5,<0.20.0)
Requires-Dist: geopandas (>=1.0.1,<2.0.0)
Requires-Dist: matplotlib (>=3.10.7,<4.0.0)
Requires-Dist: requests (>=2.32.3,<3.0.0)
Requires-Dist: shapely (>=2.0.5,<3.0.0)
Requires-Dist: tqdm (>=4.66.4,<5.0.0)
Project-URL: Documentation, https://github.com/adehecq/usgs_explorer
Project-URL: Homepage, https://github.com/adehecq/usgs_explorer
Project-URL: Repository, https://github.com/adehecq/usgs_explorer
